nextpage/__init__.py
nextpage/templates/nextpage/pagination.html
nextpage/templatetags/__init__.py
nextpage/templatetags/nextpage.py
django_nextpage-1.0.2.dist-info/LICENSE
django_nextpage-1.0.2.dist-info/METADATA
django_nextpage-1.0.2.dist-info/WHEEL
django_nextpage-1.0.2.dist-info/top_level.txt
django_nextpage-1.0.2.dist-info/RECORD
