Metadata-Version: 2.1
Name: django-nextpage
Version: 1.0.2
Summary: django-nextpage
Home-page: http://github.com/StreetVoice/django-nextpage
Author: tzangms
Author-email: tzangms@gmail.com
License: BSD
Keywords: pagination,django
Platform: UNKNOWN
Classifier: Programming Language :: Python
Classifier: Topic :: Software Development :: Libraries :: Python Modules
Classifier: Framework :: Django
Classifier: Environment :: Web Environment
